irename/__init__.py
irename/__main__.py
irename-1.0.0.dist-info/DESCRIPTION.rst
irename-1.0.0.dist-info/METADATA
irename-1.0.0.dist-info/RECORD
irename-1.0.0.dist-info/WHEEL
irename-1.0.0.dist-info/entry_points.txt
irename-1.0.0.dist-info/metadata.json
irename-1.0.0.dist-info/top_level.txt
