Metadata-Version: 2.0
Name: irename
Version: 1.0.0
Summary: interactive rename files using favorite editoror
Home-page: http://msztolcman.github.io/irename/
Author: Marcin Sztolcman
Author-email: marcin@urzenia.net
License: MIT
Keywords: file management,rename,move,terminal,cli
Platform: UNKNOWN
Classifier: Development Status :: 4 - Beta
Classifier: Environment :: Console
Classifier: Intended Audience :: Developers
Classifier: Intended Audience :: System Administrators
Classifier: License :: OSI Approved :: MIT License
Classifier: Topic :: Utilities
Classifier: Operating System :: OS Independent
Classifier: Programming Language :: Python :: 3.3
Classifier: Programming Language :: Python :: 3.4
Classifier: Programming Language :: Python :: 3.5
Requires-Dist: argparse
